[ 
    {
        "id":1,
        "color": "Red"
    },
    {
        "id":2,
        "color": "Blue"
    },
    {
        "id":3,
        "color": "Green"
    },
    {
        "id":4,
        "color": "Yellow"
    },
    {
        "id": 5,
        "color": "purple"
    },
    {
        "id":6,
        "color": "Orange"
    },
    {
        "id":7,
        "color": "Black"
    },
    {
        "id":8,
        "color": "White"
    },
    {
        "id":9,
        "color": "Pink"
    },
    {
        "id": 10,
        "color": "Brown"
    },
    {
        "id": 11,
        "color": "Grey"
    }
]